ez_setup.py
Adafruit_IO/__init__.py
Adafruit_IO/_version.py
Adafruit_IO/client.py
Adafruit_IO/errors.py
Adafruit_IO/model.py
Adafruit_IO/mqtt_client.py
adafruit_io-2.0.0.dist-info/METADATA
adafruit_io-2.0.0.dist-info/RECORD
adafruit_io-2.0.0.dist-info/WHEEL
adafruit_io-2.0.0.dist-info/top_level.txt
