Metadata-Version: 2.1
Name: adafruit-io
Version: 2.0.0
Summary: Client library for Adafruit IO (http://io.adafruit.com/).
Home-page: https://github.com/adafruit/io-client-python
Author: Justin Cooper
Author-email: justin@adafruit.com
License: MIT
Keywords: Adafruit IO
Platform: UNKNOWN
Classifier: Development Status :: 5 - Production/Stable
Classifier: Operating System :: POSIX :: Linux
Classifier: Operating System :: Microsoft :: Windows
Classifier: Operating System :: MacOS
Classifier: License :: OSI Approved :: MIT License
Classifier: Intended Audience :: Developers
Classifier: Programming Language :: Python :: 3.6
Classifier: Topic :: Software Development
Classifier: Topic :: Home Automation
Classifier: Topic :: System :: Hardware
Requires-Python: >=3.6
Requires-Dist: requests
Requires-Dist: paho-mqtt
